nonebot2_plugin_napcat_process_filtering/__init__.py
nonebot2_plugin_napcat_process_filtering/config.py
nonebot2_plugin_napcat_process_filtering-0.1.2.dist-info/METADATA
nonebot2_plugin_napcat_process_filtering-0.1.2.dist-info/WHEEL
nonebot2_plugin_napcat_process_filtering-0.1.2.dist-info/RECORD
