Metadata-Version: 2.3
Name: nonebot2-plugin-napcat-process-filtering
Version: 0.1.2
Summary: 自动同意被过滤的 QQ 好友请求的 NoneBot2 插件
License: MIT
Keywords: nonebot2,plugin,qq,napcat,自动同意被过滤的好友请求
Author: yzdd
Author-email: 2901581089@qq.com
Requires-Python: >=3.8,<4.0
Classifier: License :: OSI Approved :: MIT License
Classifier: Programming Language :: Python :: 3
Classifier: Programming Language :: Python :: 3.8
Classifier: Programming Language :: Python :: 3.9
Classifier: Programming Language :: Python :: 3.10
Classifier: Programming Language :: Python :: 3.11
Classifier: Programming Language :: Python :: 3.12
Classifier: Programming Language :: Python :: 3.13
Requires-Dist: httpx (>=0.23.0,<0.24.0)
Requires-Dist: nonebot2 (>=2.0.0,<3.0.0)
Project-URL: Homepage, https://github.com/yscdzxj/nonebot2_plugin_napcat_process_filtering
Project-URL: Repository, https://github.com/yscdzxj/nonebot2_plugin_napcat_process_filtering
